easy_django_cli/__init__.py
easy_django_cli/cli.py
easy_django_cli-0.1.2.dist-info/licenses/LICENSE
easy_django_cli-0.1.2.dist-info/METADATA
easy_django_cli-0.1.2.dist-info/WHEEL
easy_django_cli-0.1.2.dist-info/entry_points.txt
easy_django_cli-0.1.2.dist-info/top_level.txt
easy_django_cli-0.1.2.dist-info/RECORD
