Metadata-Version: 2.4
Name: easy-django-cli
Version: 0.1.2
Summary: A modern CLI tool that replaces 'python manage.py' and 'django-admin' with simpler 'django' or 'dj' commands
Author-email: Tim Kamanin <tim@timonweb.com>
License-Expression: MIT
Project-URL: Homepage, https://github.com/timonweb/easy-django-cli
Project-URL: Repository, https://github.com/timonweb/easy-django-cli
Project-URL: Issues, https://github.com/timonweb/easy-django-cli/issues
Keywords: django,cli,command-line,management,tools
Classifier: Development Status :: 3 - Alpha
Classifier: Framework :: Django :: 4.2
Classifier: Framework :: Django :: 5.0
Classifier: Framework :: Django :: 5.1
Classifier: Framework :: Django :: 5.2
Classifier: Framework :: Django :: 6.0
Classifier: Intended Audience :: Developers
Classifier: Natural Language :: English
Classifier: Operating System :: OS Independent
Classifier: Programming Language :: Python :: 3 :: Only
Classifier: Programming Language :: Python :: 3.10
Classifier: Programming Language :: Python :: 3.11
Classifier: Programming Language :: Python :: 3.12
Classifier: Programming Language :: Python :: 3.13
Classifier: Programming Language :: Python :: 3.14
Requires-Python: >=3.10
License-File: LICENSE
Requires-Dist: django>=4.2
Dynamic: license-file
